alphawordle.py
alpha_wordle-0.1.0.dist-info/LICENSE
alpha_wordle-0.1.0.dist-info/METADATA
alpha_wordle-0.1.0.dist-info/WHEEL
alpha_wordle-0.1.0.dist-info/top_level.txt
alpha_wordle-0.1.0.dist-info/RECORD
