Metadata-Version: 2.1
Name: alpha-wordle
Version: 0.1.0
Summary: alpha-wordle
Home-page: UNKNOWN
Author: Ishan Bhatt
License: UNKNOWN
Platform: UNKNOWN
Classifier: Programming Language :: Python :: 3
Classifier: License :: OSI Approved :: MIT License
Classifier: Operating System :: OS Independent
Requires-Python: >=3.6
License-File: LICENSE
